tg_converter/__init__.py
tg_converter/main.py
TGSessionsCoverter-0.0.3.dist-info/LICENSE
TGSessionsCoverter-0.0.3.dist-info/METADATA
TGSessionsCoverter-0.0.3.dist-info/WHEEL
TGSessionsCoverter-0.0.3.dist-info/top_level.txt
TGSessionsCoverter-0.0.3.dist-info/RECORD
